[
  {
    "Primary Key": "4e56f50c6329a7c6d7ebdb1fdefad0d6",
    "Country": "UK",
    "Sector": "Health",
    "Budget Currency": null,
    "Budget in Local Currency Minimum": 1,
    "Budget in Local Currency Maximum": 2,
    "Budget in INR Minimum": null,
    "Budget in INR Maximum": null,
    "Order Quantity": null,
    "Expiry Date": "6297442",
    "Opening Date": "Procurement identifier (OCID): ocds-h6vhtk-05660f (view related notices)",
    "Organisation Name": "Belfast Health & Social Care Trust",
    "Link to the Tender": "https://www.find-tender.service.gov.uk/Notice/082441-2025?origin=SearchResults&p=1",
    "Tender Title": "Surgical Dressings",
    "Tender Description": "This tendering exercise aims at renewing the compliant and effective framework for the supply and delivery of Surgical Dressings and Miscellaneous Products [3508540] which is due to expire on 30th April 2026*. This new framework will also incorporate the Aseptically Prepared Larvae which are currently covered by JDAC 4225718 which expires 31st May 2026*.\n\n*Both the existing Surgical Dressings FW [3508540] and the Aseptically Prepared Larvae JDAC [4225718] were extended by 3 and 2 months respectively (under clause 2.3, Commercial Terms and Conditions ) to 31st July 2026 allow additional time for completion of this tender.",
    "Special Observation": null,
    "Award Date": null,
    "Timeline": null,
    "Eligibility": null,
    "Keyword included": "wearable device",
    "Application Status": "Not Applied",
    "Current Applicants": null,
    "Keywords": [
      "wearable device"
    ],
    "health_score": -0.0038,
    "defence_score": 0.0114,
    "corporate_score": -0.0267,
    "pet_score": 0.0237,
    "health_pass": false,
    "defence_pass": false,
    "corporate_pass": false,
    "pets_pass": false,
    "sector": "None"
  },
  {
    "Primary Key": "02d095049539cd93df9551b99bc7ce3e",
    "Country": "UK",
    "Sector": "Health",
    "Budget Currency": null,
    "Budget in Local Currency Minimum": 1,
    "Budget in Local Currency Maximum": 2,
    "Budget in INR Minimum": null,
    "Budget in INR Maximum": null,
    "Order Quantity": null,
    "Expiry Date": "NWSSP Procurement (sourcing)",
    "Opening Date": "Procurement identifier (OCID): ocds-h6vhtk-046c73",
    "Organisation Name": "NWSSP Procurement (sourcing)",
    "Link to the Tender": "https://www.find-tender.service.gov.uk/Notice/016914-2024?origin=SearchResults&p=1",
    "Tender Title": "Prosthetic Components and Associated Consumables",
    "Tender Description": "-",
    "Special Observation": null,
    "Award Date": null,
    "Timeline": null,
    "Eligibility": null,
    "Keyword included": "wearable device",
    "Application Status": "Not Applied",
    "Current Applicants": null,
    "Keywords": [
      "wearable device"
    ],
    "health_score": -0.0038,
    "defence_score": 0.0114,
    "corporate_score": -0.0267,
    "pet_score": 0.0237,
    "health_pass": false,
    "defence_pass": false,
    "corporate_pass": false,
    "pets_pass": false,
    "sector": "None"
  },
  {
    "Primary Key": "391b288931b164fc59ef921f723cf9c7",
    "Country": "UK",
    "Sector": "Health",
    "Budget Currency": null,
    "Budget in Local Currency Minimum": 1,
    "Budget in Local Currency Maximum": 3241,
    "Budget in INR Minimum": null,
    "Budget in INR Maximum": null,
    "Order Quantity": null,
    "Expiry Date": "UNIVERSITY OF SHEFFIELD",
    "Opening Date": "Procurement identifier (OCID): ocds-h6vhtk-03480f",
    "Organisation Name": "UNIVERSITY OF SHEFFIELD",
    "Link to the Tender": "https://www.find-tender.service.gov.uk/Notice/016746-2022?origin=SearchResults&p=1",
    "Tender Title": "3325/JN - Sustainable Aviation Fuels - Innovation Centre: Further Aviation Characterisation Laboratory Equipment (14 Lots)",
    "Tender Description": "-",
    "Special Observation": null,
    "Award Date": null,
    "Timeline": null,
    "Eligibility": null,
    "Keyword included": "wearable device",
    "Application Status": "Not Applied",
    "Current Applicants": null,
    "Keywords": [
      "wearable device"
    ],
    "health_score": -0.0038,
    "defence_score": 0.0114,
    "corporate_score": -0.0267,
    "pet_score": 0.0237,
    "health_pass": false,
    "defence_pass": false,
    "corporate_pass": false,
    "pets_pass": false,
    "sector": "None"
  },
  {
    "Primary Key": "c11b7ffeb95ea0b62e8177b4f01b48e1",
    "Country": "UK",
    "Sector": "Health",
    "Budget Currency": null,
    "Budget in Local Currency Minimum": 1,
    "Budget in Local Currency Maximum": 2,
    "Budget in INR Minimum": null,
    "Budget in INR Maximum": null,
    "Order Quantity": null,
    "Expiry Date": "Secretary of State for the Home Department",
    "Opening Date": "Procurement identifier (OCID): ocds-h6vhtk-0297cf",
    "Organisation Name": "Secretary of State for the Home Department",
    "Link to the Tender": "https://www.find-tender.service.gov.uk/Notice/004206-2021?origin=SearchResults&p=1",
    "Tender Title": "Contract for the Supply and Maintenance of Trace Detection Devices",
    "Tender Description": "-",
    "Special Observation": null,
    "Award Date": null,
    "Timeline": null,
    "Eligibility": null,
    "Keyword included": "wearable device",
    "Application Status": "Not Applied",
    "Current Applicants": null,
    "Keywords": [
      "wearable device"
    ],
    "health_score": -0.0038,
    "defence_score": 0.0114,
    "corporate_score": -0.0267,
    "pet_score": 0.0237,
    "health_pass": false,
    "defence_pass": false,
    "corporate_pass": false,
    "pets_pass": false,
    "sector": "None"
  },
  {
    "Primary Key": "8e4ff90d56523a9162afbf1d78de80d5",
    "Country": "UK",
    "Sector": "Health",
    "Budget Currency": null,
    "Budget in Local Currency Minimum": null,
    "Budget in Local Currency Maximum": null,
    "Budget in INR Minimum": null,
    "Budget in INR Maximum": null,
    "Order Quantity": null,
    "Expiry Date": "The procurement will contract for commercially available off\u2011the\u2011shelf (COTS) mobile communication devices to be developed by successful suppliers to meet ESN technical, security and public safety requirements, in order to achieve ESN certification.",
    "Opening Date": "Procurement identifier (OCID): ocds-h6vhtk-055738 (view related notices)",
    "Organisation Name": "Home Office",
    "Link to the Tender": "https://www.find-tender.service.gov.uk/Notice/055923-2026?origin=SearchResults&p=1",
    "Tender Title": "Emergency Services Network (ESN) End User Devices",
    "Tender Description": "The procurement will contract for commercially available off\u2011the\u2011shelf (COTS) mobile communication devices to be developed by successful suppliers to meet ESN technical, security and public safety requirements, in order to achieve ESN certification.\n\nIndividual contracts will be awarded for each device selected. For the avoidance of doubt, if a Bidder is awarded multiple contracts, a separate contract will have to be signed for each individual device.\n\nThe Authority intends to award contracts to suppliers in order to maximise choice and operational resilience. The maximum numbers of contracts to be awarded in each lot are as follows:\n\nLot 1 - 5\n\nLot 2 - 2\n\nLot 3 - 2\n\nLot 4 - 4\n\nThe award of contracts is also subject to the following rules:\n\n1. For Lots 1 and 4, the Authority will, as default, award only four and three contracts respectively. However, the Authority requires one or more dual mode devices (ESN plus Tetra DMO) in each lot in addition to devices solely for use on the ESN. If the leading four bids making up the target number of contracts by Most Advantageous Tender (MAT) score do not include a bid for a dual mode device, the Authority may award a fifth contract to a supplier offering a dual mode device based on the highest MAT score for that device.\n\n2. Where a Bidder is relying on a sub-contractor to fulfil its contractual obligations and more than one bid is submitted based on the same device and/or sub-contractor under these conditions, the Authority reserves the right to award a contract only to the Bidder achieving the highest MAT score.\n\nIf this rule is invoked by the Authority and the MAT rankings of the relevant bidders under the rule are above that of the lowest ranking Bidder awarded a contract, the Authority reserves the right to award a contract to the Bidder or Bidders with the highest MAT ranking or rankings immediately below that of the lowest ranking successful bidder. However, the Authority is not obligated to do so.\n\nFor example, if four contracts are to be awarded in Lot 1 and two relevant bidders under this rule are placed first and third on MAT ranking, the Authority will only award a contract to the first ranked Bidder and reserves the right to award a further contract to the fifth ranked bidder if different to the first and third.\n\n3. If both this rule and rule 1 are invoked together in any Lot, the Authority reserves the right only to award any additional contract to the highest MAT ranked bid offering a dual mode device.\n\n4. Where a Bidder submits multiple bids for places on the same Lot, the Authority reserves the right, at its sole discretion, to only award contracts to up to two of those bids with the highest Most Advantageous Tender (MAT) scores provided that those scores place both bids within the maximum number of contracts to be awarded in the lot.\n\nThe scope of this procurement is limited to device development, testing and ESN certification activities. The routine supply of certified devices, accessories and associated services to operational users is expected to be delivered through call\u2011off contracts under GCA's NS4 framework (RM6377). However, the Authority may procure some developed Devices for purposes such as testing and trials. These will not be for full operational use.",
    "Special Observation": null,
    "Award Date": null,
    "Timeline": null,
    "Eligibility": null,
    "Keyword included": "wearable device",
    "Application Status": "Not Applied",
    "Current Applicants": null,
    "Keywords": [
      "wearable device"
    ],
    "health_score": -0.0038,
    "defence_score": 0.0114,
    "corporate_score": -0.0267,
    "pet_score": 0.0237,
    "health_pass": false,
    "defence_pass": false,
    "corporate_pass": false,
    "pets_pass": false,
    "sector": "None"
  },
  {
    "Primary Key": "fee01936ac578fc2d9b4925d4b15d38d",
    "Country": "UK",
    "Sector": "Health",
    "Budget Currency": null,
    "Budget in Local Currency Minimum": 1,
    "Budget in Local Currency Maximum": 2,
    "Budget in INR Minimum": null,
    "Budget in INR Maximum": null,
    "Order Quantity": null,
    "Expiry Date": "Merseyside Fire & Rescue Authority",
    "Opening Date": "Procurement identifier (OCID): ocds-h6vhtk-030c68",
    "Organisation Name": "Merseyside Fire & Rescue Authority",
    "Link to the Tender": "https://www.find-tender.service.gov.uk/Notice/022223-2022?origin=SearchResults&p=1",
    "Tender Title": "Detection, Identification and Monitoring (DIM) Equipment Uplift",
    "Tender Description": "-",
    "Special Observation": null,
    "Award Date": null,
    "Timeline": null,
    "Eligibility": null,
    "Keyword included": "wearable device",
    "Application Status": "Not Applied",
    "Current Applicants": null,
    "Keywords": [
      "wearable device"
    ],
    "health_score": -0.0038,
    "defence_score": 0.0114,
    "corporate_score": -0.0267,
    "pet_score": 0.0237,
    "health_pass": false,
    "defence_pass": false,
    "corporate_pass": false,
    "pets_pass": false,
    "sector": "None"
  },
  {
    "Primary Key": "cbc05109f1bdf4146940311f8361ada1",
    "Country": "UK",
    "Sector": "Health",
    "Budget Currency": null,
    "Budget in Local Currency Minimum": 8,
    "Budget in Local Currency Maximum": 3,
    "Budget in INR Minimum": null,
    "Budget in INR Maximum": null,
    "Order Quantity": null,
    "Expiry Date": "enFrame CIC",
    "Opening Date": "Procurement identifier (OCID): ocds-h6vhtk-030725",
    "Organisation Name": "enFrame CIC",
    "Link to the Tender": "https://www.find-tender.service.gov.uk/Notice/000144-2022?origin=SearchResults&p=1",
    "Tender Title": "Framework agreement to supply ICT goods and services to the education sector and any UK public sector body",
    "Tender Description": "-",
    "Special Observation": null,
    "Award Date": null,
    "Timeline": null,
    "Eligibility": null,
    "Keyword included": "wearable device",
    "Application Status": "Not Applied",
    "Current Applicants": null,
    "Keywords": [
      "wearable device"
    ],
    "health_score": -0.0038,
    "defence_score": 0.0114,
    "corporate_score": -0.0267,
    "pet_score": 0.0237,
    "health_pass": false,
    "defence_pass": false,
    "corporate_pass": false,
    "pets_pass": false,
    "sector": "None"
  },
  {
    "Primary Key": "3d534ff0da6376334d589484e437a8a3",
    "Country": "UK",
    "Sector": "Health",
    "Budget Currency": null,
    "Budget in Local Currency Minimum": null,
    "Budget in Local Currency Maximum": null,
    "Budget in INR Minimum": null,
    "Budget in INR Maximum": null,
    "Order Quantity": null,
    "Expiry Date": "NHS Supply Chain seeks to establish a Framework Agreement for Total Patient Assessment Device Solution Products under which it will be entitled to purchase supplies and/or services which it will make available for purchase by 1) any NHS Trust; 2) any other NHS entity; 3) any government department, agency or other statutory body and/or 4) any private sector entity active in the UK healthcare sector. Only NHS Supply Chain can order from the Framework Agreement and enter into contracts under it.",
    "Opening Date": "Procurement identifier (OCID): ocds-h6vhtk-05485c (view related notices)",
    "Organisation Name": "SUPPLY CHAIN COORDINATION LIMITED",
    "Link to the Tender": "https://www.find-tender.service.gov.uk/Notice/032216-2025?origin=SearchResults&p=1",
    "Tender Title": "Total Patient Assessment Device Solutions Tender Notice",
    "Tender Description": "NHS Supply Chain seeks to establish a Framework Agreement for Total Patient Assessment Device Solution Products under which it will be entitled to purchase supplies and/or services which it will make available for purchase by 1) any NHS Trust; 2) any other NHS entity; 3) any government department, agency or other statutory body and/or 4) any private sector entity active in the UK healthcare sector. Only NHS Supply Chain can order from the Framework Agreement and enter into contracts under it.\n\nThis includes the following requirements which have been sub-divided into Lots:\n\nLot 1 - Blood Pressure Monitoring with Blood Pressure Cuffs\n\nLot 2 - Thermometer Devices and Related Consumables\n\nLot 3 - Patient Weighing Scales and Measuring Devices\n\nLot 4 - Patient Assessment Devices and Kits\n\nLot 5 - Personal Health Monitors and Kits\n\nIt is anticipated that initial expenditure will be in the region of \u00a323,900,000 to \u00a325,000,000 in the first year of this Framework Agreement, however this is approximate only and the values may vary depending on the requirements of those bodies purchasing under the Framework Agreement. Estimated value over the 2-year Framework Agreement will be in the region of \u00a347,800,000. There will be an option to extend the Framework for a further 2 years. If the extension period will be utilised, then the total value of the Framework across the 4 year would be approximately \u00a395,600,000.\n\nPreliminary market engagement was carried out during PCR 2015, with a Prior Information Notice being published. The identifier codes for the Prior information Notice are as follows:\n\nNotice identifier: 2024/S 000-018940\n\nProcurement identifier (OCID): ocds-h6vhtk-04713a",
    "Special Observation": null,
    "Award Date": null,
    "Timeline": null,
    "Eligibility": null,
    "Keyword included": "wearable device",
    "Application Status": "Not Applied",
    "Current Applicants": null,
    "Keywords": [
      "wearable device"
    ],
    "health_score": -0.0038,
    "defence_score": 0.0114,
    "corporate_score": -0.0267,
    "pet_score": 0.0237,
    "health_pass": false,
    "defence_pass": false,
    "corporate_pass": false,
    "pets_pass": false,
    "sector": "None"
  },
  {
    "Primary Key": "0d1cc16afaedeca6a8289685b28688fb",
    "Country": "UK",
    "Sector": "Health",
    "Budget Currency": null,
    "Budget in Local Currency Minimum": 32000000,
    "Budget in Local Currency Maximum": 32000000,
    "Budget in INR Minimum": null,
    "Budget in INR Maximum": null,
    "Order Quantity": null,
    "Expiry Date": "ESMCP Commercial Team (Handheld Project)",
    "Opening Date": "Procurement identifier (OCID): ocds-h6vhtk-0287ea",
    "Organisation Name": "ESMCP Commercial Team (Handheld Project)",
    "Link to the Tender": "https://www.find-tender.service.gov.uk/Notice/000164-2021?origin=SearchResults&p=1",
    "Tender Title": "The Supply of TETRA Based Device to Device Remote Speaker Microphone (RSM) for use with LTE Handheld Mobile Devices on the Emergency Services Network (ESN)",
    "Tender Description": "-",
    "Special Observation": null,
    "Award Date": null,
    "Timeline": null,
    "Eligibility": null,
    "Keyword included": "wearable device",
    "Application Status": "Not Applied",
    "Current Applicants": null,
    "Keywords": [
      "wearable device"
    ],
    "health_score": -0.0038,
    "defence_score": 0.0114,
    "corporate_score": -0.0267,
    "pet_score": 0.0237,
    "health_pass": false,
    "defence_pass": false,
    "corporate_pass": false,
    "pets_pass": false,
    "sector": "None"
  }
]